oceanum/__init__.py
oceanum/cli.py
oceanum/datamesh/__init__.py
oceanum/datamesh/cache.py
oceanum/datamesh/catalog.py
oceanum/datamesh/connection.py
oceanum/datamesh/datasource.py
oceanum/datamesh/exceptions.py
oceanum/datamesh/query.py
oceanum/datamesh/zarr.py
oceanum/storage/__init__.py
oceanum/storage/filesystem.py
oceanum-0.14.3.dist-info/AUTHORS.rst
oceanum-0.14.3.dist-info/LICENSE
oceanum-0.14.3.dist-info/METADATA
oceanum-0.14.3.dist-info/WHEEL
oceanum-0.14.3.dist-info/entry_points.txt
oceanum-0.14.3.dist-info/top_level.txt
oceanum-0.14.3.dist-info/RECORD
