Metadata-Version: 2.1
Name: oceanum
Version: 0.14.3
Summary: Library for oceanum.io services
Author-email: Oceanum Developers <developers@oceanum.science>
Maintainer-email: Oceanum Developers <developers@oceanum.science>
License: MIT License
Project-URL: Homepage, https://oceanum.io/
Project-URL: Source, https://github.com/oceanum-io/oceanum-python
Project-URL: Documentation, https://oceanum-python.readthedocs.io/en/latest/
Project-URL: Tracker, https://github.com/oceanum-io/oceanum-python/issues
Keywords: oceanum,datamesh,oceanum.io
Classifier: Development Status :: 4 - Beta
Classifier: Intended Audience :: Science/Research
Classifier: License :: OSI Approved :: MIT License
Classifier: Natural Language :: English
Classifier: Operating System :: OS Independent
Classifier: Topic :: Scientific/Engineering
Classifier: Topic :: Scientific/Engineering :: Physics
Classifier: Topic :: Scientific/Engineering :: Visualization
Classifier: Programming Language :: Python :: 3
Classifier: Programming Language :: Python :: 3.8
Classifier: Programming Language :: Python :: 3.9
Classifier: Programming Language :: Python :: 3.10
Requires-Python: >=3.8
License-File: LICENSE
License-File: AUTHORS.rst
Requires-Dist: aiohttp
Requires-Dist: click
Requires-Dist: decorator
Requires-Dist: fsspec
Requires-Dist: geojson-pydantic
Requires-Dist: geopandas
Requires-Dist: h5netcdf
Requires-Dist: numpy
Requires-Dist: orjson
Requires-Dist: pandas
Requires-Dist: pyarrow
Requires-Dist: requests
Requires-Dist: shapely
Requires-Dist: xarray
Requires-Dist: zarr
Requires-Dist: dask[dataframe]
Requires-Dist: msgpack
Requires-Dist: cftime
Provides-Extra: docs
Requires-Dist: autodoc-pydantic ; extra == 'docs'
Requires-Dist: pydata-sphinx-theme ; extra == 'docs'
Requires-Dist: sphinx ; extra == 'docs'
Requires-Dist: sphinxcontrib-programoutput ; extra == 'docs'
Provides-Extra: eidos
Requires-Dist: oceanum.eidos ; extra == 'eidos'
Provides-Extra: test
Requires-Dist: pytest ; extra == 'test'
Requires-Dist: pytest-env ; extra == 'test'
Provides-Extra: video
Requires-Dist: xarray-video ; extra == 'video'
